geojson2imdf/__init__.py
geojson2imdf/app.py
imdf/__init__.py
imdf/base.py
imdf/venue.py
geojson2imdf-0.0.21.0.dist-info/AUTHORS.rst
geojson2imdf-0.0.21.0.dist-info/LICENSE.txt
geojson2imdf-0.0.21.0.dist-info/METADATA
geojson2imdf-0.0.21.0.dist-info/WHEEL
geojson2imdf-0.0.21.0.dist-info/entry_points.txt
geojson2imdf-0.0.21.0.dist-info/top_level.txt
geojson2imdf-0.0.21.0.dist-info/RECORD
