Metadata-Version: 2.1
Name: geojson2imdf
Version: 0.0.21.0
Summary: Add a short description here!
Home-page: https://pyscaffold.org/
Author: lucas
Author-email: lucas.selfslagh@gmail.com
License: mit
Platform: any
Classifier: Development Status :: 4 - Beta
Classifier: Programming Language :: Python
Provides-Extra: testing
Requires-Dist: pytest ; extra == 'testing'
Requires-Dist: pytest-cov ; extra == 'testing'
